Distributions_Normal_and_Binomial/Binomialdistribution.py
Distributions_Normal_and_Binomial/Gaussiandistribution.py
Distributions_Normal_and_Binomial/Generaldistribution.py
Distributions_Normal_and_Binomial/__init__.py
Distributions_Normal_and_Binomial-0.1.dist-info/METADATA
Distributions_Normal_and_Binomial-0.1.dist-info/WHEEL
Distributions_Normal_and_Binomial-0.1.dist-info/license.txt
Distributions_Normal_and_Binomial-0.1.dist-info/top_level.txt
Distributions_Normal_and_Binomial-0.1.dist-info/RECORD
