Metadata-Version: 2.1
Name: Distributions-Normal-and-Binomial
Version: 0.1
Summary: Gaussian distributions and Binomial distributions
Home-page: UNKNOWN
Author: Agney Praseed
Author-email: agneysince2000@gmail.com
License: UNKNOWN
Platform: UNKNOWN
Classifier: Programming Language :: Python :: 3
Classifier: License :: OSI Approved :: MIT License
Classifier: Operating System :: OS Independent
Requires-Python: >=3.6
License-File: license.txt
